Metadata-Version: 2.0
Name: powerline-shell
Version: 0.6.0
Summary: A pretty prompt for your shell
Home-page: https://github.com/banga/powerline-shell
Author: Buck Ryan
Author-email: buck@buckryan.com
License: MIT
Platform: UNKNOWN
Classifier: Programming Language :: Python :: 2
Classifier: Programming Language :: Python :: 2.7
Classifier: Programming Language :: Python :: 3
Classifier: Programming Language :: Python :: 3.3
Classifier: Programming Language :: Python :: 3.4
Classifier: Programming Language :: Python :: 3.5
Requires-Dist: argparse
